produksiikan/__init__.py
indonesian_fishproduction-0.1.2.2.dist-info/LICENSE
indonesian_fishproduction-0.1.2.2.dist-info/METADATA
indonesian_fishproduction-0.1.2.2.dist-info/WHEEL
indonesian_fishproduction-0.1.2.2.dist-info/top_level.txt
indonesian_fishproduction-0.1.2.2.dist-info/RECORD
