Metadata-Version: 2.1
Name: indonesian-fishproduction
Version: 0.1.2.2
Summary: This package will give us information about the marine fish productionin Indonesia
Home-page: https://github.com/wearenotrobot/indomarinefish
Author: mizan toyyibun
Author-email: untirta.mizan62@gmail.com
License: UNKNOWN
Project-URL: Bug Tracker, https://github.com/wearenotrobot/indomarinefish
Platform: UNKNOWN
Classifier: Programming Language :: Python :: 3
Classifier: License :: OSI Approved :: GNU General Public License v3 (GPLv3)
Classifier: Operating System :: OS Independent
Classifier: Development Status :: 4 - Beta
Requires-Python: >=3.6
License-File: LICENSE
